[
  {
    "Ticker": "ASML",
    "Name": "ASML Holding NV",
    "Qty": 28.39,
    "Avg Buy Price (P/S)": 663.55,
    "LTP": 763.9,
    "Buy Value": 18839,
    "Present Value": 21687.88,
    "P&L (%)": 15.123200964509085,
    "Allocation (%)": 2.43,
    "Price Change (1D)": 1.83
  },
  {
    "Ticker": "AVGO",
    "Name": "Broadcom Inc",
    "Qty": 88.02,
    "Avg Buy Price (P/S)": 181.77,
    "LTP": 232.42,
    "Buy Value": 16000,
    "Present Value": 20457.6,
    "P&L (%)": 27.86488419431148,
    "Allocation (%)": 2.29,
    "Price Change (1D)": 4.89
  },
  {
    "Ticker": "HCA",
    "Name": "HCA Healthcare Inc",
    "Qty": 15.05,
    "Avg Buy Price (P/S)": 332.22,
    "LTP": 368.1,
    "Buy Value": 5000,
    "Present Value": 5539.9,
    "P&L (%)": 10.800072241285893,
    "Allocation (%)": 0.62,
    "Price Change (1D)": 1.33
  },
  {
    "Ticker": "MSFT",
    "Name": "Microsoft Corp",
    "Qty": 92.29,
    "Avg Buy Price (P/S)": 389.74,
    "LTP": 449.14,
    "Buy Value": 35970,
    "Present Value": 41451.13,
    "P&L (%)": 15.240929850669671,
    "Allocation (%)": 4.65,
    "Price Change (1D)": -0.03
  },
  {
    "Ticker": "NKE",
    "Name": "Nike Inc",
    "Qty": 185.97,
    "Avg Buy Price (P/S)": 74.82,
    "LTP": 62.39,
    "Buy Value": 13916,
    "Present Value": 11602.66,
    "P&L (%)": -16.61320502539427,
    "Allocation (%)": 1.3,
    "Price Change (1D)": -0.3
  },
  {
    "Ticker": "NVDA",
    "Name": "NVIDIA Corp",
    "Qty": 243.88,
    "Avg Buy Price (P/S)": 108.92,
    "LTP": 129.93,
    "Buy Value": 26565,
    "Present Value": 31687.82,
    "P&L (%)": 19.28938670583915,
    "Allocation (%)": 3.55,
    "Price Change (1D)": 5.63
  },
  {
    "Ticker": "PANW",
    "Name": "Palo Alto Networks Inc",
    "Qty": 76.15,
    "Avg Buy Price (P/S)": 173.01,
    "LTP": 192,
    "Buy Value": 13175,
    "Present Value": 14620.8,
    "P&L (%)": 10.97624414773713,
    "Allocation (%)": 1.64,
    "Price Change (1D)": -0.78
  },
  {
    "Ticker": "AMD",
    "Name": "Advanced Micro Devices Inc",
    "Qty": 147.91,
    "Avg Buy Price (P/S)": 108.17,
    "LTP": 112.46,
    "Buy Value": 16000,
    "Present Value": 16634.18,
    "P&L (%)": 3.9659794767495535,
    "Allocation (%)": 1.86,
    "Price Change (1D)": 4.01
  },
  {
    "Ticker": "AMZN",
    "Name": "Amazon.com Inc",
    "Qty": 213.79,
    "Avg Buy Price (P/S)": 180.36,
    "LTP": 211.37,
    "Buy Value": 38560,
    "Present Value": 45188.79,
    "P&L (%)": 17.1933909957862,
    "Allocation (%)": 5.07,
    "Price Change (1D)": 1.31
  },
  {
    "Ticker": "NVO",
    "Name": "Novo Nordisk A/S",
    "Qty": 513.46,
    "Avg Buy Price (P/S)": 66.21,
    "LTP": 65.4,
    "Buy Value": 34000,
    "Present Value": 33580.54,
    "P&L (%)": -1.2233801540552607,
    "Allocation (%)": 3.77,
    "Price Change (1D)": -3.45
  },
  {
    "Ticker": "GOOGL",
    "Name": "Alphabet Inc Class A",
    "Qty": 317.29,
    "Avg Buy Price (P/S)": 153.23,
    "LTP": 159.53,
    "Buy Value": 48620,
    "Present Value": 50617.75,
    "P&L (%)": 4.111466423024219,
    "Allocation (%)": 5.68,
    "Price Change (1D)": 0.68
  },
  {
    "Ticker": "META",
    "Name": "Meta Platforms Inc",
    "Qty": 61.91,
    "Avg Buy Price (P/S)": 516.87,
    "LTP": 656.03,
    "Buy Value": 32000,
    "Present Value": 40614.81,
    "P&L (%)": 26.92359780989416,
    "Allocation (%)": 4.56,
    "Price Change (1D)": 2.6
  },
  {
    "Ticker": "CRWD",
    "Name": "Crowdstrike Holdings Inc",
    "Qty": 18.96,
    "Avg Buy Price (P/S)": 316.45,
    "LTP": 440.2,
    "Buy Value": 6000,
    "Present Value": 8346.19,
    "P&L (%)": 39.10570390267025,
    "Allocation (%)": 0.93,
    "Price Change (1D)": 2.51
  },
  {
    "Ticker": "NFLX",
    "Name": "Netflix Inc",
    "Qty": 18.58,
    "Avg Buy Price (P/S)": 861.14,
    "LTP": 1138.44,
    "Buy Value": 16000,
    "Present Value": 21152.21,
    "P&L (%)": 32.201500336762905,
    "Allocation (%)": 2.37,
    "Price Change (1D)": 2.56
  },
  {
    "Ticker": "MELI",
    "Name": "MercadoLibre Inc",
    "Qty": 6.06,
    "Avg Buy Price (P/S)": 1978.23,
    "LTP": 2515.12,
    "Buy Value": 12000,
    "Present Value": 15256.71,
    "P&L (%)": 27.13991800751176,
    "Allocation (%)": 1.71,
    "Price Change (1D)": 0.42
  },
  {
    "Ticker": "AAPL",
    "Name": "Apple Inc",
    "Qty": 47.26,
    "Avg Buy Price (P/S)": 172.42,
    "LTP": 212.93,
    "Buy Value": 8150,
    "Present Value": 10064.54,
    "P&L (%)": 23.494954181649476,
    "Allocation (%)": 1.13,
    "Price Change (1D)": 1.02
  },
  {
    "Ticker": "LLY",
    "Name": "Eli Lilly And Co",
    "Qty": 17.18,
    "Avg Buy Price (P/S)": 756.29,
    "LTP": 746.06,
    "Buy Value": 13000,
    "Present Value": 12824.02,
    "P&L (%)": -1.3526557273003768,
    "Allocation (%)": 1.44,
    "Price Change (1D)": -1.26
  },
  {
    "Ticker": "NU",
    "Name": "Nu Holdings Ltd",
    "Qty": 1167.07,
    "Avg Buy Price (P/S)": 11.99,
    "LTP": 13.14,
    "Buy Value": 14000,
    "Present Value": 15335.36,
    "P&L (%)": 9.591326105087576,
    "Allocation (%)": 1.72,
    "Price Change (1D)": 1.47
  },
  {
    "Ticker": "UNH",
    "Name": "UnitedHealth Group Inc",
    "Qty": 33.29,
    "Avg Buy Price (P/S)": 389.21,
    "LTP": 311.38,
    "Buy Value": 12960,
    "Present Value": 10368.33,
    "P&L (%)": -19.996916831530534,
    "Allocation (%)": 1.16,
    "Price Change (1D)": -17.79
  },
  {
    "Ticker": "TSM",
    "Name": "Taiwan Semicndctr Mnufctrng Co Ltd",
    "Qty": 36.63,
    "Avg Buy Price (P/S)": 163.79,
    "LTP": 193.99,
    "Buy Value": 6000,
    "Present Value": 7106.04,
    "P&L (%)": 18.438244093045984,
    "Allocation (%)": 0.79,
    "Price Change (1D)": 3.75
  },
  {
    "Ticker": "ADBE",
    "Name": "Adobe Inc",
    "Qty": 7.57,
    "Avg Buy Price (P/S)": 395.93,
    "LTP": 397.4,
    "Buy Value": 3000,
    "Present Value": 3011.09,
    "P&L (%)": 0.3712777511176143,
    "Allocation (%)": 0.33,
    "Price Change (1D)": 0.37
  },
  {
    "Ticker": "BOTZ",
    "Name": "Global X Robotics and Artificial Intelligence ETF",
    "Qty": 245.79,
    "Avg Buy Price (P/S)": 34.58,
    "LTP": 31.03,
    "Buy Value": 8500,
    "Present Value": 7626.86,
    "P&L (%)": -10.266049739733942,
    "Allocation (%)": 0.85,
    "Price Change (1D)": 1.37
  },
  {
    "Ticker": "QQQM",
    "Name": "Invesco NASDAQ 100 ETF",
    "Qty": 489.59,
    "Avg Buy Price (P/S)": 192.44,
    "LTP": 212.27,
    "Buy Value": 94219,
    "Present Value": 103926.54,
    "P&L (%)": 10.304510496778223,
    "Allocation (%)": 11.66,
    "Price Change (1D)": 1.53
  },
  {
    "Ticker": "IVV",
    "Name": "iShares Core S&P 500 ETF",
    "Qty": 123.28,
    "Avg Buy Price (P/S)": 517.55,
    "LTP": 589.94,
    "Buy Value": 63808,
    "Present Value": 72732.4,
    "P&L (%)": 13.98705439088013,
    "Allocation (%)": 8.16,
    "Price Change (1D)": 0.72
  },
  {
    "Ticker": "XLK",
    "Name": "Technology Select Sector SPDR Fund",
    "Qty": 180.18,
    "Avg Buy Price (P/S)": 230.29,
    "LTP": 232.62,
    "Buy Value": 41495,
    "Present Value": 41913.47,
    "P&L (%)": 1.0117677710712636,
    "Allocation (%)": 4.7,
    "Price Change (1D)": 2.16
  },
  {
    "Ticker": "IYW",
    "Name": "iShares US Technology ETF",
    "Qty": 147.7,
    "Avg Buy Price (P/S)": 162.09,
    "LTP": 158.67,
    "Buy Value": 23942,
    "Present Value": 23435.55,
    "P&L (%)": -2.1099389228206653,
    "Allocation (%)": 2.63,
    "Price Change (1D)": 2.2
  },
  {
    "Ticker": "SOXX",
    "Name": "iShares Semiconductor ETF",
    "Qty": 263.86,
    "Avg Buy Price (P/S)": 185.12,
    "LTP": 213.76,
    "Buy Value": 48847,
    "Present Value": 56404.06,
    "P&L (%)": 15.471045808124453,
    "Allocation (%)": 6.33,
    "Price Change (1D)": 2.83
  },
  {
    "Ticker": "FXI",
    "Name": "iShares China Large-Cap ETF",
    "Qty": 299.81,
    "Avg Buy Price (P/S)": 36.76,
    "LTP": 35.74,
    "Buy Value": 11022,
    "Present Value": 10715.2,
    "P&L (%)": -2.774755168661578,
    "Allocation (%)": 1.2,
    "Price Change (1D)": -0.83
  },
  {
    "Ticker": "IJR",
    "Name": "iShares Core S&P Small-Cap ETF",
    "Qty": 235.43,
    "Avg Buy Price (P/S)": 101.98,
    "LTP": 108.02,
    "Buy Value": 24010,
    "Present Value": 25431.47,
    "P&L (%)": 5.922729947048433,
    "Allocation (%)": 2.85,
    "Price Change (1D)": 0.47
  },
  {
    "Ticker": "VOO",
    "Name": "Vanguard S&P 500 ETF",
    "Qty": 107.52,
    "Avg Buy Price (P/S)": 467.81,
    "LTP": 539.44,
    "Buy Value": 50300,
    "Present Value": 58001.66,
    "P&L (%)": 15.311771873196395,
    "Allocation (%)": 6.51,
    "Price Change (1D)": 0.66
  },
  {
    "Ticker": "BTCUSD",
    "Name": "Bitcoin ",
    "Qty": 0.51,
    "Avg Buy Price (P/S)": 85329.28,
    "LTP": 103862,
    "Buy Value": 43719,
    "Present Value": 53214.35,
    "P&L (%)": 21.719062905488013,
    "Allocation (%)": 5.97,
    "Price Change (1D)": -0.3
  }
]