[
  {
    "Ticker": "ASML",
    "Name": "ASML Holding NV",
    "Qty": 28.39,
    "Avg Buy Price (P/S)": 663.55,
    "LTP": 745.62,
    "Buy Value": 18839,
    "Present Value": 21168.89,
    "P&L (%)": 12.368321904905441,
    "Allocation (%)": 2.6,
    "Price Change (1D)": -0.12
  },
  {
    "Ticker": "AVGO",
    "Name": "Broadcom Inc",
    "Qty": 88.02,
    "Avg Buy Price (P/S)": 181.77,
    "LTP": 240.58,
    "Buy Value": 16000,
    "Present Value": 21175.85,
    "P&L (%)": 32.35407382956483,
    "Allocation (%)": 2.6,
    "Price Change (1D)": 0.48
  },
  {
    "Ticker": "HCA",
    "Name": "HCA Healthcare Inc",
    "Qty": 15.05,
    "Avg Buy Price (P/S)": 332.22,
    "LTP": 378.84,
    "Buy Value": 5000,
    "Present Value": 5701.54,
    "P&L (%)": 14.032869785082159,
    "Allocation (%)": 0.7,
    "Price Change (1D)": 0.06
  },
  {
    "Ticker": "MSFT",
    "Name": "Microsoft Corp",
    "Qty": 92.29,
    "Avg Buy Price (P/S)": 389.74,
    "LTP": 457.6,
    "Buy Value": 35970,
    "Present Value": 42231.9,
    "P&L (%)": 17.411607738492332,
    "Allocation (%)": 5.18,
    "Price Change (1D)": 0.05
  },
  {
    "Ticker": "NKE",
    "Name": "Nike Inc",
    "Qty": 185.97,
    "Avg Buy Price (P/S)": 74.82,
    "LTP": 61.37,
    "Buy Value": 13916,
    "Present Value": 11412.97,
    "P&L (%)": -17.976476877840145,
    "Allocation (%)": 1.4,
    "Price Change (1D)": -0.63
  },
  {
    "Ticker": "NVDA",
    "Name": "NVIDIA Corp",
    "Qty": 243.88,
    "Avg Buy Price (P/S)": 108.92,
    "LTP": 138.91,
    "Buy Value": 26565,
    "Present Value": 33877.9,
    "P&L (%)": 27.533969886154967,
    "Allocation (%)": 4.16,
    "Price Change (1D)": 3.04
  },
  {
    "Ticker": "PANW",
    "Name": "Palo Alto Networks Inc",
    "Qty": 141.39,
    "Avg Buy Price (P/S)": 178.04,
    "LTP": 184.57,
    "Buy Value": 25175,
    "Present Value": 26098.01,
    "P&L (%)": 3.6677151201977094,
    "Allocation (%)": 3.2,
    "Price Change (1D)": -1.72
  },
  {
    "Ticker": "AMD",
    "Name": "Advanced Micro Devices Inc",
    "Qty": 236.78,
    "Avg Buy Price (P/S)": 109.8,
    "LTP": 112.39,
    "Buy Value": 26000,
    "Present Value": 26612.6,
    "P&L (%)": 2.358834244080149,
    "Allocation (%)": 3.26,
    "Price Change (1D)": -0.42
  },
  {
    "Ticker": "AMZN",
    "Name": "Amazon.com Inc",
    "Qty": 213.79,
    "Avg Buy Price (P/S)": 180.36,
    "LTP": 205.16,
    "Buy Value": 38560,
    "Present Value": 43861.15,
    "P&L (%)": 13.750277223331105,
    "Allocation (%)": 5.38,
    "Price Change (1D)": 0.21
  },
  {
    "Ticker": "NVO",
    "Name": "Novo Nordisk A/S",
    "Qty": 513.46,
    "Avg Buy Price (P/S)": 66.21,
    "LTP": 69.04,
    "Buy Value": 34000,
    "Present Value": 35449.55,
    "P&L (%)": 4.274278809847474,
    "Allocation (%)": 4.35,
    "Price Change (1D)": 0.61
  },
  {
    "Ticker": "GOOGL",
    "Name": "Alphabet Inc Class A",
    "Qty": 317.29,
    "Avg Buy Price (P/S)": 153.23,
    "LTP": 171.41,
    "Buy Value": 48620,
    "Present Value": 54387.19,
    "P&L (%)": 11.864517392155587,
    "Allocation (%)": 6.68,
    "Price Change (1D)": -0.55
  },
  {
    "Ticker": "META",
    "Name": "Meta Platforms Inc",
    "Qty": 61.91,
    "Avg Buy Price (P/S)": 516.87,
    "LTP": 643.67,
    "Buy Value": 32000,
    "Present Value": 39849.6,
    "P&L (%)": 24.532280844312872,
    "Allocation (%)": 4.89,
    "Price Change (1D)": 0.01
  },
  {
    "Ticker": "CRWD",
    "Name": "Crowdstrike Holdings Inc",
    "Qty": 18.96,
    "Avg Buy Price (P/S)": 316.45,
    "LTP": 458.56,
    "Buy Value": 6000,
    "Present Value": 8694.29,
    "P&L (%)": 44.90756833623006,
    "Allocation (%)": 1.06,
    "Price Change (1D)": -2.19
  },
  {
    "Ticker": "NFLX",
    "Name": "Netflix Inc",
    "Qty": 18.58,
    "Avg Buy Price (P/S)": 861.14,
    "LTP": 1177.59,
    "Buy Value": 16000,
    "Present Value": 21879.62,
    "P&L (%)": 36.74779942866432,
    "Allocation (%)": 2.68,
    "Price Change (1D)": -2.56
  },
  {
    "Ticker": "MELI",
    "Name": "MercadoLibre Inc",
    "Qty": 6.06,
    "Avg Buy Price (P/S)": 1978.23,
    "LTP": 2538.77,
    "Buy Value": 12000,
    "Present Value": 15400.17,
    "P&L (%)": 28.335431168266577,
    "Allocation (%)": 1.89,
    "Price Change (1D)": -0.47
  },
  {
    "Ticker": "AAPL",
    "Name": "Apple Inc",
    "Qty": 0,
    "Avg Buy Price (P/S)": 0,
    "LTP": 198.89,
    "Buy Value": 0,
    "Present Value": 0,
    "P&L (%)": 0.13249238799478033,
    "Allocation (%)": 0,
    "Price Change (1D)": -0.76
  },
  {
    "Ticker": "LLY",
    "Name": "Eli Lilly And Co",
    "Qty": 17.18,
    "Avg Buy Price (P/S)": 756.29,
    "LTP": 720.51,
    "Buy Value": 13000,
    "Present Value": 12384.84,
    "P&L (%)": -4.730989435269536,
    "Allocation (%)": 1.52,
    "Price Change (1D)": 0.16
  },
  {
    "Ticker": "NU",
    "Name": "Nu Holdings Ltd",
    "Qty": 1167.07,
    "Avg Buy Price (P/S)": 11.99,
    "LTP": 12.02,
    "Buy Value": 14000,
    "Present Value": 14028.24,
    "P&L (%)": 0.2502085070892357,
    "Allocation (%)": 1.72,
    "Price Change (1D)": -1.39
  },
  {
    "Ticker": "UNH",
    "Name": "UnitedHealth Group Inc",
    "Qty": 73.17,
    "Avg Buy Price (P/S)": 314.33,
    "LTP": 297.64,
    "Buy Value": 23000,
    "Present Value": 21778.61,
    "P&L (%)": -5.309706359558426,
    "Allocation (%)": 2.67,
    "Price Change (1D)": -0.1
  },
  {
    "Ticker": "TSM",
    "Name": "Taiwan Semicndctr Mnufctrng Co Ltd",
    "Qty": 77.25,
    "Avg Buy Price (P/S)": 181.22,
    "LTP": 196.56,
    "Buy Value": 14000,
    "Present Value": 15184.26,
    "P&L (%)": 8.464849354375898,
    "Allocation (%)": 1.86,
    "Price Change (1D)": 0.22
  },
  {
    "Ticker": "ADBE",
    "Name": "Adobe Inc",
    "Qty": 24.37,
    "Avg Buy Price (P/S)": 410.29,
    "LTP": 412.04,
    "Buy Value": 10000,
    "Present Value": 10042.65,
    "P&L (%)": 0.4265275780545468,
    "Allocation (%)": 1.23,
    "Price Change (1D)": -0.05
  },
  {
    "Ticker": "TMO",
    "Name": "Thermo Fisher Scientific Inc",
    "Qty": 24.64,
    "Avg Buy Price (P/S)": 405.71,
    "LTP": 403.5,
    "Buy Value": 10000,
    "Present Value": 9945.46,
    "P&L (%)": -0.5447240639865865,
    "Allocation (%)": 1.22,
    "Price Change (1D)": 0.36
  },
  {
    "Ticker": "TMDX",
    "Name": "TransMedics Group Inc",
    "Qty": 38.68,
    "Avg Buy Price (P/S)": 129.23,
    "LTP": 126.86,
    "Buy Value": 5000,
    "Present Value": 4908.08,
    "P&L (%)": -1.8339394877350388,
    "Allocation (%)": 0.6,
    "Price Change (1D)": -1.37
  },
  {
    "Ticker": "BOTZ",
    "Name": "Global X Robotics and Artificial Intelligence ETF",
    "Qty": 245.79,
    "Avg Buy Price (P/S)": 34.58,
    "LTP": 31.3,
    "Buy Value": 8500,
    "Present Value": 7693.22,
    "P&L (%)": -9.485251590514741,
    "Allocation (%)": 0.94,
    "Price Change (1D)": 0.69
  },
  {
    "Ticker": "QQQM",
    "Name": "Invesco NASDAQ 100 ETF",
    "Qty": 372.58,
    "Avg Buy Price (P/S)": 192.44,
    "LTP": 213.54,
    "Buy Value": 71700.55200205884,
    "Present Value": 79561.16,
    "P&L (%)": 10.964456453959674,
    "Allocation (%)": 9.77,
    "Price Change (1D)": -0.06
  },
  {
    "Ticker": "IVV",
    "Name": "iShares Core S&P 500 ETF",
    "Qty": 0,
    "Avg Buy Price (P/S)": 0,
    "LTP": 591.66,
    "Buy Value": 0,
    "Present Value": 0,
    "P&L (%)": 15.36,
    "Allocation (%)": 0,
    "Price Change (1D)": 0.21
  },
  {
    "Ticker": "XLK",
    "Name": "Technology Select Sector SPDR Fund",
    "Qty": 180.18,
    "Avg Buy Price (P/S)": 230.29,
    "LTP": 230.86,
    "Buy Value": 41495,
    "Present Value": 41596.35,
    "P&L (%)": 0.24751400408181928,
    "Allocation (%)": 5.11,
    "Price Change (1D)": -0.16
  },
  {
    "Ticker": "IYW",
    "Name": "iShares US Technology ETF",
    "Qty": 147.7,
    "Avg Buy Price (P/S)": 162.09,
    "LTP": 158.23,
    "Buy Value": 23942,
    "Present Value": 23370.57,
    "P&L (%)": -2.3813930532420344,
    "Allocation (%)": 2.87,
    "Price Change (1D)": -0.01
  },
  {
    "Ticker": "SOXX",
    "Name": "iShares Semiconductor ETF",
    "Qty": 263.86,
    "Avg Buy Price (P/S)": 185.12,
    "LTP": 208.08,
    "Buy Value": 48847,
    "Present Value": 54905.3,
    "P&L (%)": 12.402765773552295,
    "Allocation (%)": 6.74,
    "Price Change (1D)": -0.08
  },
  {
    "Ticker": "FXI",
    "Name": "iShares China Large-Cap ETF",
    "Qty": 0,
    "Avg Buy Price (P/S)": 0,
    "LTP": 35.59,
    "Buy Value": 0,
    "Present Value": 0,
    "P&L (%)": -0.041434911994193344,
    "Allocation (%)": 0,
    "Price Change (1D)": 0.98
  },
  {
    "Ticker": "IJR",
    "Name": "iShares Core S&P Small-Cap ETF",
    "Qty": 235.43,
    "Avg Buy Price (P/S)": 101.98,
    "LTP": 105.61,
    "Buy Value": 24010,
    "Present Value": 24864.07,
    "P&L (%)": 3.5595214747989754,
    "Allocation (%)": 3.05,
    "Price Change (1D)": 0.25
  },
  {
    "Ticker": "VOO",
    "Name": "Vanguard S&P 500 ETF",
    "Qty": 91.22,
    "Avg Buy Price (P/S)": 476.24,
    "LTP": 541.11,
    "Buy Value": 43447.802926793665,
    "Present Value": 49364.92,
    "P&L (%)": 13.621283386527802,
    "Allocation (%)": 6.06,
    "Price Change (1D)": 0.16
  },
  {
    "Ticker": "XLV",
    "Name": "Health Care Select Sector SPDR Fund",
    "Qty": 91.13,
    "Avg Buy Price (P/S)": 131.68,
    "LTP": 132.17,
    "Buy Value": 12000,
    "Present Value": 12044.65,
    "P&L (%)": 0.3721142162818808,
    "Allocation (%)": 1.47,
    "Price Change (1D)": 0.52
  },
  {
    "Ticker": "BTCUSD",
    "Name": "Bitcoin ",
    "Qty": 0.42,
    "Avg Buy Price (P/S)": 85329.28,
    "LTP": 105752.1,
    "Buy Value": 36056.43045554677,
    "Present Value": 44686.22,
    "P&L (%)": 23.934129058630294,
    "Allocation (%)": 5.49,
    "Price Change (1D)": -0.58
  }
]